ffile_man/__init__.py
ffile_man/fits_file/__init__.py
ffile_man/fits_file/fits_file.py
ffile_man/manager/__init__.py
ffile_man/manager/manager.py
ffile_man-0.2.1.dist-info/LICENSE
ffile_man-0.2.1.dist-info/METADATA
ffile_man-0.2.1.dist-info/WHEEL
ffile_man-0.2.1.dist-info/RECORD
