Metadata-Version: 2.1
Name: ffile-man
Version: 0.2.1
Summary: FITS file manager
License: MIT
Author: Bernardes, D. and Balaji T R
Requires-Python: >=3.10,<4.0
Classifier: License :: OSI Approved :: MIT License
Classifier: Programming Language :: Python :: 3
Classifier: Programming Language :: Python :: 3.10
Classifier: Programming Language :: Python :: 3.11
Classifier: Programming Language :: Python :: 3.12
Requires-Dist: poetry-plugin-export (>=1.8.0,<2.0.0)
Requires-Dist: setuptools (>=70.3.0,<71.0.0)
